<annotation>
	<folder>color_sim</folder>
	<filename>left1174.jpg</filename>
	<path>/Users/vmpustak/Tech/ML/udacity/carnd/term3/CarND-Capstone/imgs/traffic_light_training/color_sim/left1174.jpg</path>
	<source>
		<database>Unknown</database>
	</source>
	<size>
		<width>800</width>
		<height>600</height>
		<depth>3</depth>
	</size>
	<segmented>0</segmented>
	<object>
		<name>yellow_light</name>
		<pose>Unspecified</pose>
		<truncated>0</truncated>
		<difficult>0</difficult>
		<bndbox>
			<xmin>532</xmin>
			<ymin>417</ymin>
			<xmax>562</xmax>
			<ymax>485</ymax>
		</bndbox>
	</object>
	<object>
		<name>yellow_light</name>
		<pose>Unspecified</pose>
		<truncated>0</truncated>
		<difficult>0</difficult>
		<bndbox>
			<xmin>673</xmin>
			<ymin>419</ymin>
			<xmax>704</xmax>
			<ymax>487</ymax>
		</bndbox>
	</object>
</annotation>
